ant_cli/__init__.py
ant_cli/__main__.py
ant_cli/ffmpeg_utils.py
ant_cli/storage.py
ant_cli/utils.py
ant_cli/commands/__init__.py
ant_cli/commands/change_prof.py
ant_cli/commands/docker.py
ant_cli/commands/ffcheck.py
ant_cli/commands/get_value.py
ant_cli/commands/list_profiles.py
ant_cli/commands/podman.py
ant_cli/commands/set_value.py
ant_cli/commands/version.py
anitypetools-0.3.0.dist-info/METADATA
anitypetools-0.3.0.dist-info/WHEEL
anitypetools-0.3.0.dist-info/entry_points.txt
anitypetools-0.3.0.dist-info/top_level.txt
anitypetools-0.3.0.dist-info/RECORD
